Metadata-Version: 2.4
Name: hello_world_bvarade
Version: 0.1.0
Summary: this is the simple hello world library
Author: Bhushan Varade
Author-email: Bhushan Varade <bvarade02@gmail.com>
License: MIT
Keywords: hello,world,example
Requires-Python: >=3.6
License-File: LICENSE
Dynamic: author
Dynamic: license-file
Dynamic: requires-python
